inputapi/__init__.py
inputapi/RDCs/_RDCs.py
inputapi/RDCs/__init__.py
inputapi/boolean/__init__.py
inputapi/boolean/_boolean.py
inputapi/menus/__init__.py
inputapi/menus/multiSelect/__init__.py
inputapi/menus/multiSelect/returnDeselected/__init__.py
inputapi/menus/multiSelect/returnDeselected/_returnDeselected.py
inputapi/menus/multiSelect/returnSelected/__init__.py
inputapi/menus/multiSelect/returnSelected/_returnSelected.py
inputapi/menus/singleSelect/__init__.py
inputapi/menus/singleSelect/_singleSelect.py
inputapi/numerical/__init__.py
inputapi/numerical/float/__init__.py
inputapi/numerical/float/_float.py
inputapi/numerical/integer/__init__.py
inputapi/numerical/integer/_integer.py
inputapi/otherFunc/__init__.py
inputapi/otherFunc/clearScreen/__init__.py
inputapi/otherFunc/clearScreen/_clearScreen.py
inputapi/otherFunc/pause/__init__.py
inputapi/otherFunc/pause/_pause.py
inputapi/strings/__init__.py
inputapi/strings/_strings.py
inputapi-2.1.3.dist-info/METADATA
inputapi-2.1.3.dist-info/WHEEL
inputapi-2.1.3.dist-info/licenses/LICENSE
inputapi-2.1.3.dist-info/RECORD
