Metadata-Version: 2.4
Name: inputapi
Version: 2.1.3
Summary: A simpler way to get user input
Project-URL: github, https://github.com/HomerHaddock/Input-API
Author-email: Homer Haddock <homerhaddock@proton.me>
License:                     GNU GENERAL PUBLIC LICENSE
License-File: LICENSE
Classifier: License :: OSI Approved :: GNU General Public License v2 (GPLv2)
Classifier: Operating System :: OS Independent
Classifier: Programming Language :: Python :: 3
Requires-Python: >=3.7
